flySkyiBus/IBus.py
flySkyiBus/__init__.py
flySkyiBus-1.0.0.dist-info/LICENSE
flySkyiBus-1.0.0.dist-info/METADATA
flySkyiBus-1.0.0.dist-info/WHEEL
flySkyiBus-1.0.0.dist-info/top_level.txt
flySkyiBus-1.0.0.dist-info/RECORD
