Metadata-Version: 2.1
Name: flySkyiBus
Version: 1.0.0
Summary: FlySky iBus python library for the raspberry pi.
Home-page: https://github.com/GamerHegi64/FlySky-Ibus
Author: GamerHegi64
Author-email: gamerhegi64@gmail.de
License-File: LICENSE
Requires-Dist: pyserial (>=3.4)
